{"guid":"root________","title":"","index":0,"dateAdded":1522082545972000,"lastModified":1522858162126000,"id":1,"typeCode":2,"type":"text/x-moz-place-container","root":"placesRoot","children":[{"guid":"menu________","title":"书签菜单","index":0,"dateAdded":1522082545972000,"lastModified":1522421651896000,"id":2,"typeCode":2,"type":"text/x-moz-place-container","root":"bookmarksMenuFolder","children":[{"guid":"Pqx7hdClJ3Z4","title":"","index":0,"dateAdded":1522082547248000,"lastModified":1522082547248000,"id":20,"typeCode":3,"type":"text/x-moz-place-separator"},{"guid":"HG3w71a3DjSd","title":"Mozilla Firefox","index":1,"dateAdded":1522082546910000,"lastModified":1522236383888000,"id":7,"typeCode":2,"annos":[{"name":"bookmarkPropertiesDialog/folderLastUsed","flags":0,"expires":4,"value":1522236382686}],"type":"text/x-moz-place-container","children":[{"guid":"XqIG6nJnEjtf","title":"帮助和教程","index":0,"dateAdded":1522082546910000,"lastModified":1522082546910000,"id":8,"typeCode":1,"iconuri":"fake-favicon-uri:https://support.mozilla.org/zh-CN/products/firefox","type":"text/x-moz-place","uri":"https://support.mozilla.org/zh-CN/products/firefox"},{"guid":"BUpvMqACulXn","title":"自定义 Firefox","index":1,"dateAdded":1522082546910000,"lastModified":1522082546910000,"id":9,"typeCode":1,"iconuri":"fake-favicon-uri:https://www.mozilla.org/zh-CN/firefox/customize/","type":"text/x-moz-place","uri":"https://www.mozilla.org/zh-CN/firefox/customize/"},{"guid":"sJuq2FBlt4Wp","title":"加入进来","index":2,"dateAdded":1522082546910000,"lastModified":1522082546910000,"id":10,"typeCode":1,"iconuri":"fake-favicon-uri:https://www.mozilla.org/zh-CN/contribute/","type":"text/x-moz-place","uri":"https://www.mozilla.org/zh-CN/contribute/"},{"guid":"HeXnnp8Lzbar","title":"关于我们","index":3,"dateAdded":1522082546910000,"lastModified":1522082546910000,"id":11,"typeCode":1,"iconuri":"fake-favicon-uri:https://www.mozilla.org/zh-CN/about/","type":"text/x-moz-place","uri":"https://www.mozilla.org/zh-CN/about/"}]},{"guid":"6bjHQD7XJ2YV","title":"最近使用的标签","index":2,"dateAdded":1522421651896000,"lastModified":1522421652415000,"id":59,"typeCode":1,"annos":[{"name":"Places/SmartBookmark","flags":0,"expires":4,"value":"RecentTags"}],"type":"text/x-moz-place","uri":"place:type=6&sort=14&maxResults=10"},{"guid":"u9TxVXo51yGb","title":"","index":3,"dateAdded":1304104956810000,"lastModified":1304104956810000,"id":52,"typeCode":3,"type":"text/x-moz-place-separator"}]},{"guid":"toolbar_____","title":"书签工具栏","index":1,"dateAdded":1522082545972000,"lastModified":1522858162126000,"id":3,"typeCode":2,"type":"text/x-moz-place-container","root":"toolbarFolder","children":[{"guid":"FFB7JfmM9L76","title":"最常访问","index":0,"dateAdded":1522421650836000,"lastModified":1522421650921000,"id":58,"typeCode":1,"annos":[{"name":"Places/SmartBookmark","flags":0,"expires":4,"value":"MostVisited"}],"type":"text/x-moz-place","uri":"place:sort=8&maxResults=10"},{"guid":"sdLPccKJJTEk","title":"","index":1,"dateAdded":1304106352478000,"lastModified":1304106352478000,"id":49,"typeCode":3,"type":"text/x-moz-place-separator"},{"guid":"oTI3-wm6kvgx","title":"百度","index":2,"dateAdded":1522236512086000,"lastModified":1522236528830000,"id":57,"typeCode":1,"iconuri":"https://gss0.bdstatic.com/5bd1bjqh_Q23odCf/static/wiseindex/img/screen_icon_new.png#tippytop","type":"text/x-moz-place","uri":"https://www.baidu.com/"},{"guid":"69fwp6vwYDiH","title":"Google","index":3,"dateAdded":1520064923578000,"lastModified":1520064923578000,"id":40,"typeCode":1,"iconuri":"https://www.google.com.hk/images/branding/product_ios/3x/gsa_ios_60dp.png#tippytop","type":"text/x-moz-place","uri":"https://www.google.com.hk/"},{"guid":"8LpshDGEbLei","title":"GitHub","index":4,"dateAdded":1520049791784000,"lastModified":1522196741002000,"id":39,"typeCode":1,"iconuri":"https://github.com/fluidicon.png","annos":[{"name":"bookmarkProperties/description","flags":0,"expires":4,"value":"GitHub is where people build software. More than 28 million people use GitHub to discover, fork, and contribute to over 79 million projects."}],"type":"text/x-moz-place","uri":"https://github.com/"},{"guid":"NhK4oS_FFfv7","title":"Hexo","index":5,"dateAdded":1520174308471000,"lastModified":1521219356718000,"id":29,"typeCode":2,"annos":[{"name":"bookmarkProperties/description","flags":0,"expires":4,"value":"个人博客相关\n"}],"type":"text/x-moz-place-container","children":[{"guid":"8hnuWg-ROG3r","title":"Hexo","index":0,"dateAdded":1520049810562000,"lastModified":1522196741052000,"id":42,"typeCode":1,"iconuri":"https://hexo.io/icon/favicon-196x196.png","annos":[{"name":"bookmarkProperties/description","flags":0,"expires":4,"value":"Hexo is a fast, simple & powerful blog framework powered by Node.js."}],"type":"text/x-moz-place","uri":"https://hexo.io/"},{"guid":"cAA185-1juQs","title":"Markdown编辑器语法指南 - SegmentFault 思否","index":1,"dateAdded":1520179533756000,"lastModified":1522196741309000,"id":47,"typeCode":1,"annos":[{"name":"bookmarkProperties/description","flags":0,"expires":4,"value":"SegmentFault ( www.sf.gg ) 是中国领先的开发者技术社区。 我们希望为编程爱好者提供一个纯粹、高质的技术交流的平台， 与开发者一起学习、交流与成长，创造属于开发者的时代！"}],"type":"text/x-moz-place","uri":"https://segmentfault.com/markdown#articleHeader1"},{"guid":"mDzCCWcZfAoE","title":"NexT 使用文档","index":2,"dateAdded":1520179712516000,"lastModified":1520179712516000,"id":41,"typeCode":1,"type":"text/x-moz-place","uri":"http://theme-next.iissnan.com/"},{"guid":"0l5t2wjhEmA6","title":"hexo next主题集成gitment评论系统 - CSDN博客","index":3,"dateAdded":1520007951914000,"lastModified":1522196741152000,"id":43,"typeCode":1,"annos":[{"name":"bookmarkProperties/description","flags":0,"expires":4,"value":"简介本文介绍hexo next主题(5.1.2)集成giment评论系统的过程。所谓gitment就是把评论放到github的issues系统里，评论支持md，比较适合程序员. \n一.注册OAuth Application点击https://github.com/settings/applications/new注册，注意Authorization callback URL填自己的网站urlhttp"}],"type":"text/x-moz-place","uri":"http://blog.csdn.net/yanzi1225627/article/details/77890414"},{"guid":"rObPC057jvky","title":"Hexo静态博客搭建+个人定制 - CSDN博客","index":4,"dateAdded":1520007927092000,"lastModified":1522196740767000,"id":34,"typeCode":1,"annos":[{"name":"bookmarkProperties/description","flags":0,"expires":4,"value":"很早以前就想写这样一篇了，因为各种原因耽搁到现在（逃）...网上关于Hexo的教程其实已经有挺多了，但是很多都是一笔带过。这篇博客除了**Hexo**博客的搭建过程，还有一些我加进去的**个人定制**模块，以及**博客如何被搜索引擎（百度、谷歌）收录、如何进行SEO优化**等等，以及在这过程中遇到的数不胜数的坑。虽然时隔一个月，有些搭建过程遇到的问题记不太清了orz...但是有什么问题还是可以问我"}],"type":"text/x-moz-place","uri":"http://blog.csdn.net/lemonxq/article/details/72676005"},{"guid":"vbiup3Hp2kyK","title":"Typora — a markdown editor, markdown reader.","index":5,"dateAdded":1521219356718000,"lastModified":1521219356718000,"id":48,"typeCode":1,"type":"text/x-moz-place","uri":"https://typora.io/#"}]},{"guid":"ohdp8hB4chJm","title":"bolg","index":6,"dateAdded":1521217303967000,"lastModified":1522628566975000,"id":30,"typeCode":2,"annos":[{"name":"bookmarkPropertiesDialog/folderLastUsed","flags":0,"expires":4,"value":1522628566974}],"type":"text/x-moz-place-container","children":[{"guid":"PxCS7lptoBK3","title":"徐亮偉架构师之路~ - 自动化运维","index":0,"dateAdded":1521217321959000,"lastModified":1522196740669000,"id":33,"typeCode":1,"annos":[{"name":"bookmarkProperties/description","flags":0,"expires":4,"value":"运维 架构 Python Linux Lvs mysql proxy nginx php redis docker elk saltstack openstac"}],"type":"text/x-moz-place","uri":"http://www.xuliangwei.com/"},{"guid":"JiINuWzWgfh1","title":"suoning - 博客园","index":1,"dateAdded":1521217761045000,"lastModified":1521217761045000,"id":37,"typeCode":1,"type":"text/x-moz-place","uri":"http://www.cnblogs.com/suoning"},{"guid":"TydS3TVkXJTD","title":"赤木晴子梦 - 博客园","index":2,"dateAdded":1521217866765000,"lastModified":1521217866765000,"id":32,"typeCode":1,"type":"text/x-moz-place","uri":"http://www.cnblogs.com/Wxtrkbc"},{"guid":"48wh_UHdcGnD","title":"武沛齐 - 博客园","index":3,"dateAdded":1521218065694000,"lastModified":1521218065694000,"id":31,"typeCode":1,"type":"text/x-moz-place","uri":"http://www.cnblogs.com/wupeiqi"},{"guid":"7gdrQd6N8HNP","title":"金角大王 - 博客园","index":4,"dateAdded":1521218148118000,"lastModified":1521218148118000,"id":44,"typeCode":1,"type":"text/x-moz-place","uri":"http://www.cnblogs.com/alex3714/"},{"guid":"STPR71XGKFbS","title":"linhaifeng - 博客园","index":5,"dateAdded":1521245023345000,"lastModified":1521245023345000,"id":36,"typeCode":1,"type":"text/x-moz-place","uri":"http://www.cnblogs.com/linhaifeng/"},{"guid":"RGRbtLWDwq9r","title":"海燕。 - 博客园","index":6,"dateAdded":1521283879630000,"lastModified":1521283879630000,"id":50,"typeCode":1,"type":"text/x-moz-place","uri":"http://www.cnblogs.com/haiyan123/"},{"guid":"xzW3eogFDabC","title":"Fixdq - 博客园","index":7,"dateAdded":1522052140286000,"lastModified":1522052140286000,"id":35,"typeCode":1,"type":"text/x-moz-place","uri":"http://www.cnblogs.com/fixdq/"},{"guid":"jdIqoNQpEWt3","title":"Python3 教程 | 菜鸟教程","index":8,"dateAdded":1522628431500000,"lastModified":1522628440000000,"id":64,"typeCode":1,"charset":"UTF-8","iconuri":"http://static.runoob.com/images/icon/mobile-icon.png","annos":[{"name":"bookmarkProperties/description","flags":0,"expires":4,"value":"Python 3 教程    Python的3.0版本，常被称为Python 3000，或简称Py3k。相对于Python的早期版本，这是一个较大的升级。为了不带入过多的累赘，Python 3.0在设计的时候没有考虑向下兼容。 Python 介绍及安装教程我们在Python 2.X版本的教程中已有介绍，这里就不再赘述。 你也可以点击 Python2.x与3​​.x版本区别 来查看两者的不同。 本教程主要针对Python 3.x版本的学习.."}],"type":"text/x-moz-place","uri":"http://www.runoob.com/python3/python3-tutorial.html"},{"guid":"sWemjZIondZk","title":"Python教程 - 廖雪峰的官方网站","index":9,"dateAdded":1522628562206000,"lastModified":1522628566936000,"id":65,"typeCode":1,"charset":"UTF-8","annos":[{"name":"bookmarkProperties/description","flags":0,"expires":4,"value":"研究互联网产品和技术，提供原创中文精品教程"}],"type":"text/x-moz-place","uri":"https://www.liaoxuefeng.com/wiki/0014316089557264a6b348958f449949df42a6d3a2e542c000"}]},{"guid":"UIx3gG3xXCEQ","title":"Linux","index":7,"dateAdded":1522233871370000,"lastModified":1522824793050000,"id":53,"typeCode":2,"annos":[{"name":"bookmarkPropertiesDialog/folderLastUsed","flags":0,"expires":4,"value":1522824793048}],"type":"text/x-moz-place-container","children":[{"guid":"ihvvJ8ILA5JU","title":"Ubuntu学习——第一篇 - R_e - 博客园","index":0,"dateAdded":1522233879784000,"lastModified":1522233885450000,"id":54,"typeCode":1,"charset":"UTF-8","type":"text/x-moz-place","uri":"http://www.cnblogs.com/resn/p/5800922.html"},{"guid":"tVVutUC_PR6w","title":"中文文档 · XX-net/XX-Net Wiki","index":1,"dateAdded":1520056399333000,"lastModified":1522236440456000,"id":38,"typeCode":1,"iconuri":"https://github.com/fluidicon.png","annos":[{"name":"bookmarkProperties/description","flags":0,"expires":4,"value":"GitHub is where people build software. More than 28 million people use GitHub to discover, fork, and contribute to over 79 million projects."}],"type":"text/x-moz-place","uri":"https://github.com/XX-net/XX-Net/wiki/%E4%B8%AD%E6%96%87%E6%96%87%E6%A1%A3"},{"guid":"Wgc6c1_FkaSV","title":"Ubuntu","index":2,"dateAdded":1522082546910000,"lastModified":1522236480070000,"id":13,"typeCode":1,"iconuri":"fake-favicon-uri:http://www.ubuntu.com/","type":"text/x-moz-place","uri":"http://www.ubuntu.com/"},{"guid":"k30ryW06dB15","title":"Ubuntu Wiki (community-edited website)","index":3,"dateAdded":1522082546910000,"lastModified":1522236482168000,"id":14,"typeCode":1,"iconuri":"fake-favicon-uri:http://wiki.ubuntu.com/","type":"text/x-moz-place","uri":"http://wiki.ubuntu.com/"},{"guid":"54Um2G6nkCT5","title":"Make a Support Request to the Ubuntu Community","index":4,"dateAdded":1522082546910000,"lastModified":1522236484348000,"id":15,"typeCode":1,"iconuri":"fake-favicon-uri:https://answers.launchpad.net/ubuntu/+addquestion","type":"text/x-moz-place","uri":"https://answers.launchpad.net/ubuntu/+addquestion"},{"guid":"3eXkojga7vfo","title":"Debian (Ubuntu is based on Debian)","index":5,"dateAdded":1522082546910000,"lastModified":1522236486300000,"id":16,"typeCode":1,"iconuri":"fake-favicon-uri:http://www.debian.org/","type":"text/x-moz-place","uri":"http://www.debian.org/"},{"guid":"wdXfp3L2WMgm","title":"阿里云开元镜像站","index":6,"dateAdded":1522647069376000,"lastModified":1522647096106000,"id":66,"typeCode":1,"charset":"UTF-8","iconuri":"https://img.alicdn.com/tfs/TB1HZMhOpXXXXXgXpXXXXXXXXXX-32-32.png","annos":[{"name":"bookmarkProperties/description","flags":0,"expires":4,"value":"阿里云开源镜像站由阿里巴巴的天基团队支持。 目前提供 Debian、Ubuntu、 Fedora、Arch Linux、 CentOS、openSUSE、Scientific Linux、Gentoo 等多个发行版的软件安装源和ISO下载服务，我们竭力为互联网用户提供全面，高效和稳定的软件服务。"}],"type":"text/x-moz-place","uri":"https://opsx.alibaba.com/"},{"guid":"D3Yi_kU1JhGw","title":"清华大学开源软件镜像站 | Tsinghua Open Source Mirror","index":7,"dateAdded":1522647380370000,"lastModified":1522647383706000,"id":67,"typeCode":1,"charset":"UTF-8","iconuri":"https://mirrors.tuna.tsinghua.edu.cn/static/img/favicon.png","annos":[{"name":"bookmarkProperties/description","flags":0,"expires":4,"value":"清华大学开源软件镜像站，致力于为国内和校内用户提供高质量的开源软件镜像、Linux镜像源服务，帮助用户更方便地获取开源软件。本镜像站由清华大学TUNA团队负责维护。"}],"type":"text/x-moz-place","uri":"https://mirrors.tuna.tsinghua.edu.cn/"},{"guid":"kBVawP8GipqX","title":"Ubuntu 17.10安装之后需要做的9件事_Linux教程_Linux公社-Linux系统门户网站","index":8,"dateAdded":1522766274216000,"lastModified":1522766277536000,"id":68,"typeCode":1,"charset":"UTF-8","annos":[{"name":"bookmarkProperties/description","flags":0,"expires":4,"value":"Ubuntu 17.10 已经正式发布了，如果你正尝试试用新系统的功能，那就跟着系统极客每次 Ubuntu 发布之后的老生常谈&mdash;&mdash;U"}],"type":"text/x-moz-place","uri":"https://www.linuxidc.com/Linux/2017-10/147878.htm"},{"guid":"9TFK6Gk9YvXw","title":"Index of /","index":9,"dateAdded":1522824787994000,"lastModified":1522824793042000,"id":69,"typeCode":1,"charset":"UTF-8","type":"text/x-moz-place","uri":"http://cdimage.ubuntu.com/"}]},{"guid":"hFPyVM3b1DZr","title":"github","index":8,"dateAdded":1522236330440000,"lastModified":1522236381434000,"id":55,"typeCode":2,"type":"text/x-moz-place-container"},{"guid":"3Z-1SLC2iG4w","title":"Python","index":9,"dateAdded":1522236449114000,"lastModified":1522236471524000,"id":56,"typeCode":2,"type":"text/x-moz-place-container","children":[{"guid":"S7G0ifYbARjt","title":"Python3 基本数据类型 | 菜鸟教程","index":0,"dateAdded":1509216463598000,"lastModified":1522236464214000,"id":46,"typeCode":1,"iconuri":"http://static.runoob.com/images/icon/mobile-icon.png","annos":[{"name":"bookmarkProperties/description","flags":0,"expires":4,"value":"Python3 基本数据类型  Python 中的变量不需要声明。每个变量在使用前都必须赋值，变量赋值以后该变量才会被创建。 在 Python 中，变量就是变量，它没有类型，我们所说的“类型”是变量所指的内存中对象的类型。 等号（=）用来给变量赋值。 等号（=）运算符左边是一个变量名,等号（=）运算符右边是存储在变量中的值。例如：   实例(Python 3.0+)   [mycode3 type='python'].."}],"type":"text/x-moz-place","uri":"http://www.runoob.com/python3/python3-data-type.html"},{"guid":"FjR6l84fJxSo","title":"Python简介 - 廖雪峰的官方网站","index":1,"dateAdded":1514486390589000,"lastModified":1522236471524000,"id":45,"typeCode":1,"annos":[{"name":"bookmarkProperties/description","flags":0,"expires":4,"value":"研究互联网产品和技术，提供原创中文精品教程"}],"type":"text/x-moz-place","uri":"https://www.liaoxuefeng.com/wiki/0014316089557264a6b348958f449949df42a6d3a2e542c000/001431608990315a01b575e2ab041168ff0df194698afac000"}]},{"guid":"UwBGfcVtomJ8","title":"wallpaper","index":10,"dateAdded":1522425284786000,"lastModified":1522425304172000,"id":60,"typeCode":2,"annos":[{"name":"bookmarkPropertiesDialog/folderLastUsed","flags":0,"expires":4,"value":1522425304170}],"type":"text/x-moz-place-container","children":[{"guid":"fz3LB2O_yLu7","title":"Awesome Wallpapers - wallhaven.cc","index":0,"dateAdded":1522425297274000,"lastModified":1522425304166000,"id":61,"typeCode":1,"charset":"UTF-8","annos":[{"name":"bookmarkProperties/description","flags":0,"expires":4,"value":"Your source for the best high quality wallpapers on the Net!"}],"type":"text/x-moz-place","uri":"https://alpha.wallhaven.cc/"}]},{"guid":"bqewXOuv4hBB","title":"email","index":11,"dateAdded":1522549364948000,"lastModified":1522549881312000,"id":62,"typeCode":2,"annos":[{"name":"bookmarkPropertiesDialog/folderLastUsed","flags":0,"expires":4,"value":1522549881310}],"type":"text/x-moz-place-container","children":[{"guid":"ckGbQotrfosA","title":"阿里邮箱个人版","index":0,"dateAdded":1522549872342000,"lastModified":1522549881304000,"id":63,"typeCode":1,"charset":"UTF-8","iconuri":"https://mail.aliyun.com/static/5211206/images/favicon.ico","type":"text/x-moz-place","uri":"https://mail.aliyun.com/alimail/#h=WyJmbV8yIixbIjIiLCIiLHsiZklkIjoiMSIsInNlbElkIjoiMV8wOkR6enp6eVpEdmo4JC0tLTBULVJRM2c5MCIsIm9mZnNldCI6MCwicmciOltbIm1haWxfc2Vzc2lvbl92aWV3Iix7ImlkIjoiRHp6enp5WkR2ajgtLS0wVC1RUkMxLiIsIm1haWxJZCI6IjFfMDpEenp6enlaRHZqOCQtLS0wVC1SUTNnOTAiLCJzZiI6MCwibmV3VGFiIjpmYWxzZX1dXX0seyJsYWJlbCI6IumCruS7tiJ9XV0="}]},{"guid":"lQ47CTReBi3e","title":"ProcessOn","index":12,"dateAdded":1522857714508000,"lastModified":1522857736560000,"id":70,"typeCode":1,"charset":"UTF-8","annos":[{"name":"bookmarkProperties/description","flags":0,"expires":4,"value":"ProcessOn是一个在线协作绘图平台，为用户提供最强大、易用的作图工具！支持在线创作流程图、思维导图、BPMN、UML图、UI界面原型设计、iOS界面原型设计等。同时依托于互联网实现了人与人之间的实时协作和共享。"}],"type":"text/x-moz-place","uri":"https://www.processon.com/"},{"guid":"DFBwCTaYE2V4","title":"微信网页版","index":13,"dateAdded":1522858156142000,"lastModified":1522858162126000,"id":71,"typeCode":1,"charset":"UTF-8","iconuri":"https://res.wx.qq.com/a/wx_fed/webwx/res/static/img/qMUjOdv.png","type":"text/x-moz-place","uri":"https://wx.qq.com/"}]},{"guid":"unfiled_____","title":"其他书签","index":3,"dateAdded":1522082545972000,"lastModified":1522858162126000,"id":5,"typeCode":2,"type":"text/x-moz-place-container","root":"unfiledBookmarksFolder"},{"guid":"mobile______","title":"mobile","index":4,"dateAdded":1522082545972000,"lastModified":1522082546886000,"id":6,"typeCode":2,"annos":[{"name":"mobile/bookmarksRoot","flags":0,"expires":4,"value":1}],"type":"text/x-moz-place-container","root":"mobileFolder"}]}